rdkit_cli/__init__.py
rdkit_cli/__main__.py
rdkit_cli/cli.py
rdkit_cli/commands/__init__.py
rdkit_cli/commands/align.py
rdkit_cli/commands/conformers.py
rdkit_cli/commands/convert.py
rdkit_cli/commands/deduplicate.py
rdkit_cli/commands/depict.py
rdkit_cli/commands/descriptors.py
rdkit_cli/commands/diversity.py
rdkit_cli/commands/enumerate.py
rdkit_cli/commands/filter.py
rdkit_cli/commands/fingerprints.py
rdkit_cli/commands/fragment.py
rdkit_cli/commands/info.py
rdkit_cli/commands/mcs.py
rdkit_cli/commands/merge.py
rdkit_cli/commands/mmp.py
rdkit_cli/commands/props.py
rdkit_cli/commands/protonate.py
rdkit_cli/commands/reactions.py
rdkit_cli/commands/rgroup.py
rdkit_cli/commands/rings.py
rdkit_cli/commands/rmsd.py
rdkit_cli/commands/sample.py
rdkit_cli/commands/sascorer.py
rdkit_cli/commands/scaffold.py
rdkit_cli/commands/similarity.py
rdkit_cli/commands/split.py
rdkit_cli/commands/standardize.py
rdkit_cli/commands/stats.py
rdkit_cli/commands/validate.py
rdkit_cli/core/__init__.py
rdkit_cli/core/align.py
rdkit_cli/core/conformers.py
rdkit_cli/core/deduplicate.py
rdkit_cli/core/depict.py
rdkit_cli/core/descriptors.py
rdkit_cli/core/diversity.py
rdkit_cli/core/enumerate.py
rdkit_cli/core/filters.py
rdkit_cli/core/fingerprints.py
rdkit_cli/core/fragment.py
rdkit_cli/core/info.py
rdkit_cli/core/mcs.py
rdkit_cli/core/merge.py
rdkit_cli/core/mmp.py
rdkit_cli/core/protonate.py
rdkit_cli/core/reactions.py
rdkit_cli/core/rgroup.py
rdkit_cli/core/rings.py
rdkit_cli/core/rmsd.py
rdkit_cli/core/sample.py
rdkit_cli/core/sascorer.py
rdkit_cli/core/scaffold.py
rdkit_cli/core/similarity.py
rdkit_cli/core/split.py
rdkit_cli/core/standardizer.py
rdkit_cli/core/stats.py
rdkit_cli/core/validate.py
rdkit_cli/io/__init__.py
rdkit_cli/io/formats.py
rdkit_cli/io/readers.py
rdkit_cli/io/writers.py
rdkit_cli/parallel/__init__.py
rdkit_cli/parallel/batch.py
rdkit_cli/parallel/executor.py
rdkit_cli/progress/__init__.py
rdkit_cli/progress/ninja.py
rdkit_cli/utils/__init__.py
rdkit_cli-0.3.0.dist-info/METADATA
rdkit_cli-0.3.0.dist-info/WHEEL
rdkit_cli-0.3.0.dist-info/entry_points.txt
rdkit_cli-0.3.0.dist-info/licenses/LICENSE
rdkit_cli-0.3.0.dist-info/RECORD
