Metadata-Version: 2.4
Name: rdkit-cli
Version: 0.3.0
Summary: A comprehensive CLI tool for RDKit cheminformatics operations
Project-URL: Homepage, https://github.com/vitruves/rdkit-cli
Project-URL: Repository, https://github.com/vitruves/rdkit-cli
Project-URL: Issues, https://github.com/vitruves/rdkit-cli/issues
Author: Johan HG Natter
License-Expression: Apache-2.0
License-File: LICENSE
Keywords: cheminformatics,chemistry,cli,fingerprints,molecular-descriptors,rdkit
Classifier: Development Status :: 4 - Beta
Classifier: Environment :: Console
Classifier: Intended Audience :: Science/Research
Classifier: License :: OSI Approved :: Apache Software License
Classifier: Operating System :: OS Independent
Classifier: Programming Language :: Python :: 3
Classifier: Programming Language :: Python :: 3.10
Classifier: Programming Language :: Python :: 3.11
Classifier: Programming Language :: Python :: 3.12
Classifier: Topic :: Scientific/Engineering :: Chemistry
Requires-Python: >=3.10
Requires-Dist: numpy>=1.24.0
Requires-Dist: pandas>=2.0.0
Requires-Dist: pyarrow>=14.0.0
Requires-Dist: rdkit>=2024.3.1
Requires-Dist: rich-argparse>=1.4.0
Provides-Extra: dev
Requires-Dist: mypy>=1.0.0; extra == 'dev'
Requires-Dist: pytest-cov>=4.0.0; extra == 'dev'
Requires-Dist: pytest>=7.0.0; extra == 'dev'
Requires-Dist: ruff>=0.1.0; extra == 'dev'
